bitwarden2keepass/__init__.py
bitwarden2keepass/convert.py
bitwarden2keepass-0.0.1.dist-info/LICENSE
bitwarden2keepass-0.0.1.dist-info/METADATA
bitwarden2keepass-0.0.1.dist-info/WHEEL
bitwarden2keepass-0.0.1.dist-info/entry_points.txt
bitwarden2keepass-0.0.1.dist-info/top_level.txt
bitwarden2keepass-0.0.1.dist-info/RECORD
