Metadata-Version: 2.1
Name: bitwarden2keepass
Version: 0.0.1
Summary: Convert Bitwarden data to KeePass
Home-page: https://github.com/bakuteyev/bitwarden2keepass
Author: Anton Bakuteev
Author-email: bakuteyev@gmail.com
Classifier: Programming Language :: Python :: 3
Classifier: License :: OSI Approved :: MIT License
Classifier: Development Status :: 3 - Alpha
Classifier: Operating System :: OS Independent
Requires-Python: >=3.9
License-File: LICENSE
Requires-Dist: pykeepass
Provides-Extra: test
Requires-Dist: pytest ; extra == 'test'
Requires-Dist: coverage[toml] ; extra == 'test'
Requires-Dist: pytest-cov ; extra == 'test'
